<dreamlo><leaderboard><entry><name>jonathan</name><score>12422</score><seconds>0</seconds><text/><date>1/4/2016 10:37:40 PM</date></entry><entry><name>God</name><score>12317</score><seconds>0</seconds><text/><date>12/26/2015 5:10:58 AM</date></entry><entry><name>Cthulhu's+Eye</name><score>7226</score><seconds>0</seconds><text/><date>1/9/2016 2:50:16 AM</date></entry><entry><name>Hand+Of+Cthulhu</name><score>6960</score><seconds>0</seconds><text/><date>12/23/2015 3:32:48 AM</date></entry><entry><name>TheBloodyPoohBear</name><score>6449</score><seconds>0</seconds><text/><date>12/23/2015 2:27:39 AM</date></entry><entry><name>jono</name><score>5957</score><seconds>0</seconds><text/><date>1/4/2016 10:34:03 PM</date></entry><entry><name>My+Name</name><score>4668</score><seconds>0</seconds><text/><date>1/8/2016 3:09:57 AM</date></entry><entry><name>Scott</name><score>4003</score><seconds>0</seconds><text/><date>12/23/2015 12:48:49 AM</date></entry><entry><name>jonathan4</name><score>3584</score><seconds>0</seconds><text/><date>12/23/2015 2:24:21 AM</date></entry><entry><name>jonathan3</name><score>3504</score><seconds>0</seconds><text/><date>12/23/2015 2:20:07 AM</date></entry><entry><name>20</name><score>2521</score><seconds>0</seconds><text/><date>12/21/2015 9:54:23 AM</date></entry><entry><name>Lol</name><score>2199</score><seconds>0</seconds><text/><date>12/23/2015 6:12:41 AM</date></entry><entry><name>Jonathan2</name><score>1948</score><seconds>0</seconds><text/><date>12/23/2015 2:14:53 AM</date></entry><entry><name>PoohBear</name><score>1870</score><seconds>0</seconds><text/><date>12/23/2015 2:19:47 AM</date></entry><entry><name>C'thulhu</name><score>1685</score><seconds>0</seconds><text/><date>12/19/2015 1:49:49 AM</date></entry><entry><name>Lost</name><score>1282</score><seconds>0</seconds><text/><date>1/9/2016 3:36:09 AM</date></entry><entry><name>Z0rox</name><score>1242</score><seconds>0</seconds><text/><date>12/18/2015 10:17:05 PM</date></entry><entry><name>Another+name</name><score>1230</score><seconds>0</seconds><text/><date>12/19/2015 1:54:07 AM</date></entry><entry><name>Jonathan</name><score>1062</score><seconds>0</seconds><text/><date>12/23/2015 2:13:47 AM</date></entry><entry><name>Two+Letter+(2)</name><score>1054</score><seconds>0</seconds><text/><date>12/19/2015 12:40:33 AM</date></entry><entry><name>Your+Name</name><score>951</score><seconds>0</seconds><text/><date>12/19/2015 12:38:44 AM</date></entry><entry><name>Cthulhu's+Hand</name><score>892</score><seconds>0</seconds><text/><date>12/20/2015 7:58:51 AM</date></entry><entry><name>23894289)</name><score>789</score><seconds>0</seconds><text/><date>12/19/2015 12:42:00 AM</date></entry><entry><name>YOur</name><score>663</score><seconds>0</seconds><text/><date>12/18/2015 11:34:11 PM</date></entry><entry><name>Epic</name><score>652</score><seconds>0</seconds><text/><date>12/18/2015 11:30:47 PM</date></entry><entry><name>Another+Name</name><score>650</score><seconds>0</seconds><text/><date>12/20/2015 8:00:13 AM</date></entry><entry><name>Dave</name><score>612</score><seconds>0</seconds><text/><date>12/18/2015 10:14:22 PM</date></entry><entry><name>wqdqdqwd</name><score>540</score><seconds>0</seconds><text/><date>12/18/2015 11:37:26 PM</date></entry><entry><name>{}{}[][</name><score>396</score><seconds>0</seconds><text/><date>12/18/2015 11:28:54 PM</date></entry><entry><name>TotallyNotCheating</name><score>357</score><seconds>0</seconds><text/><date>12/18/2015 10:16:07 PM</date></entry><entry><name>your+name</name><score>310</score><seconds>0</seconds><text/><date>12/18/2015 11:37:56 PM</date></entry><entry><name>wdwfefdxcve</name><score>295</score><seconds>0</seconds><text/><date>12/18/2015 10:15:04 PM</date></entry><entry><name>this+is+sparta</name><score>271</score><seconds>0</seconds><text/><date>12/19/2015 1:42:19 AM</date></entry><entry><name>notworking</name><score>258</score><seconds>0</seconds><text/><date>12/19/2015 1:40:50 AM</date></entry><entry><name>Another</name><score>257</score><seconds>0</seconds><text/><date>1/9/2016 3:37:05 AM</date></entry><entry><name>another+low+one</name><score>220</score><seconds>0</seconds><text/><date>12/19/2015 1:43:28 AM</date></entry><entry><name>HandOfCthulhu</name><score>220</score><seconds>0</seconds><text/><date>12/18/2015 10:03:15 PM</date></entry><entry><name>DSFe2223</name><score>178</score><seconds>0</seconds><text/><date>12/19/2015 12:43:04 AM</date></entry><entry><name>344434</name><score>168</score><seconds>0</seconds><text/><date>12/19/2015 1:35:50 AM</date></entry><entry><name>lowest</name><score>135</score><seconds>0</seconds><text/><date>12/19/2015 12:46:40 AM</date></entry><entry><name>fawefwaef</name><score>117</score><seconds>0</seconds><text/><date>1/4/2016 10:38:39 PM</date></entry><entry><name>NewPerson</name><score>94</score><seconds>0</seconds><text/><date>12/21/2015 9:10:23 PM</date></entry><entry><name>Last</name><score>64</score><seconds>0</seconds><text/><date>12/18/2015 11:34:37 PM</date></entry><entry><name>NEW+LAST</name><score>57</score><seconds>0</seconds><text/><date>1/9/2016 8:32:48 PM</date></entry></leaderboard></dreamlo>